chipy_chipy/__init__.py
chipy_chipy/cfile.py
chipy_chipy/dfile.py
chipy_chipy/greet.py
chipy_chipy/math.py
chipy_chipy/rfile.py
chipy_chipy/wfile.py
chipy_chipy-1.0.8.dist-info/licenses/LICENSE
chipy_chipy-1.0.8.dist-info/METADATA
chipy_chipy-1.0.8.dist-info/WHEEL
chipy_chipy-1.0.8.dist-info/top_level.txt
chipy_chipy-1.0.8.dist-info/RECORD
