Metadata-Version: 2.4
Name: chipy-chipy
Version: 1.0.8
Summary: A python module that isnt really that good yet, usually only used for file management
Author-email: ChipDev <skylertruitt6655@gmail.com>
License-Expression: MIT
Project-URL: Docs, https://sites.google.com/view/chipy-docs/home
Classifier: Programming Language :: Python :: 3
Classifier: Operating System :: OS Independent
Requires-Python: >=3.9
License-File: LICENSE
Dynamic: license-file
